minioslcc.cpython-312-x86_64-linux-gnu.so
miniosl/__init__.py
miniosl/dataset.py
miniosl/drawing.py
miniosl/inference.py
miniosl/network.py
miniosl/player.py
miniosl/puzzle.py
miniosl/record.py
miniosl/search.py
miniosl/ui.py
miniosl/usi_process.py
miniosl/widget.py
miniosl/pretrained/eval-aozora.onnx
miniosl/pretrained/eval.onnx
miniosl/pretrained/eval.onnx.data
miniosl/sample/puzzle1.json
miniosl/sample/puzzle2.json
miniosl/sample/checkmate/A1-2.json
miniosl/sample/checkmate/A1-3-1.json
miniosl/sample/checkmate/A1-3-2.json
miniosl/sample/checkmate/A1-4-1.json
miniosl/sample/checkmate/A1-4-2.json
miniosl/sample/checkmate/A1-5-1.json
miniosl/sample/checkmate/A1-5-2.json
miniosl/sample/checkmate/A2-1.json
miniosl/sample/checkmate/A2-2.json
miniosl/sample/checkmate/A2-3.json
miniosl/sample/checkmate/A2-4.json
miniosl/sample/checkmate/A3-1.json
miniosl/sample/checkmate/A3-2.json
miniosl/sample/checkmate/A3-3.json
miniosl/sample/checkmate/A3-4.json
miniosl/sample/checkmate/B1-1.json
miniosl/sample/checkmate/B1-2.json
miniosl/sample/checkmate/B1-3.json
miniosl/sample/checkmate/B1-4.json
miniosl/sample/checkmate/B1-5.json
miniosl/sample/checkmate/B1-6.json
miniosl/sample/checkmate/B1-7.json
miniosl/sample/checkmate/B1-8.json
miniosl/sample/checkmate/B2-1.json
miniosl/sample/checkmate/B2-2.json
miniosl/sample/checkmate/B2-3.json
miniosl/sample/checkmate/B2-4.json
miniosl/sample/checkmate/B2-5.json
miniosl/sample/checkmate/B2-6.json
miniosl/sample/checkmate/B2-7.json
miniosl/sample/checkmate/B2-8.json
miniosl/sample/checkmate/B3-1.json
miniosl/sample/checkmate/B3-2.json
miniosl/sample/checkmate/B3-3.json
miniosl/sample/checkmate/B3-4.json
miniosl/sample/checkmate/B3-5.json
miniosl/sample/checkmate/B3-6.json
miniosl/sample/checkmate/B3-7.json
miniosl/sample/checkmate/B4-1.json
miniosl/sample/checkmate/B4-2.json
miniosl/sample/checkmate/B4-3.json
miniosl/sample/checkmate/B4-4.json
miniosl/sample/checkmate/B5-1.json
miniosl-0.1.8.dist-info/METADATA
miniosl-0.1.8.dist-info/WHEEL
miniosl-0.1.8.dist-info/entry_points.txt
miniosl-0.1.8.dist-info/RECORD
miniosl-0.1.8.dist-info/licenses/AUTHORS.osl
miniosl-0.1.8.dist-info/licenses/LICENSE.osl
