Metadata-Version: 2.1
Name: miniosl
Version: 0.1.8
Summary: A python interface to miniosl (shogi library)
Author-Email: "T. Kaneko" <kaneko@graco.c.u-tokyo.ac.jp>
Classifier: Topic :: Games/Entertainment :: Board Games
Classifier: Development Status :: 3 - Alpha
Classifier: Operating System :: POSIX :: Linux
Classifier: Operating System :: MacOS :: MacOS X
Classifier: Intended Audience :: Developers
Classifier: Intended Audience :: Education
Classifier: Intended Audience :: Science/Research
Project-URL: Repository, https://github.com/tkaneko/miniosl
Requires-Python: >=3.10
Requires-Dist: recordclass
Requires-Dist: numpy
Requires-Dist: matplotlib
Requires-Dist: coloredlogs
Requires-Dist: tqdm
Requires-Dist: click
Provides-Extra: infer-cpu
Requires-Dist: torch; extra == "infer-cpu"
Requires-Dist: onnxruntime; extra == "infer-cpu"
Provides-Extra: infer-gpu
Requires-Dist: torch; extra == "infer-gpu"
Requires-Dist: onnxruntime-gpu; extra == "infer-gpu"
Provides-Extra: test
Requires-Dist: pytest; extra == "test"
